{"Accountant":61364,"AccurateCountDown":28843,"AdventurerInNeed":36942,"BetterPartyFinder":27751,"BigPlayerDebuffs":14169,"BrowserHost.Plugin":11530,"Browsingway":8726,"BurntToast":12200,"ChatAlerts":3888,"ChatBubbles":171723,"ChatCoordinates":36049,"ChatExtender":2679,"ChatTyper":2337,"ChillFrames":2956,"Compass":18838,"CurrencyAlert":6019,"DailyDuty":138941,"Dalamud.DiscordBridge":42015,"Dalamud.FindAnything":33121,"Dalamud.FullscreenCutscenes":104,"Dalamud.LoadingImage":87798,"Dalamud.RichPresence":90860,"DalamudVox":55,"DamageInfoPlugin":148654,"DeathRecap":12585,"DeepDungeonDex":49131,"DelvUI":141383,"DeviceChangeFix":3013,"EasyEyes":18825,"Echoglossian":14760,"EnemyListDebuffs":28811,"EngageTimer":123942,"ExpandedSearchInfo":25241,"FCNameColor":66858,"FPSPlugin":116600,"FauxHollowsSolver":42381,"FlashOnTell":15706,"FlyTextFilter":2724,"GatherBuddy":287541,"GentleTouch":3201,"Glamaholic":15071,"Globetrotter":118729,"GoodMemory":114915,"HarpHero":27549,"Housemate":32705,"InventoryTools":29559,"ItemSearchPlugin":145672,"JobBars":177485,"JobIcons":25913,"JustBackup":7506,"Kapture":56217,"KingdomHeartsPlugin":5101,"MOAction":58467,"MPTickBar":23165,"MacroChain":8100,"MapLinker":28490,"MarketBoardPlugin":165711,"Mini":6022,"MiniCactpotSolver":144539,"NamePlateDebuffs":6743,"Namingway":2466,"NeatNoter":68598,"NoSoliciting":53733,"NoTankYou":109253,"NotificationMaster":6233,"OopsAllLalafells":55227,"PartyIcons":45462,"PatMe":15071,"PeepingTom":142985,"PennyPincher":110244,"PingPlugin":347543,"PixelPerfect":117507,"PlayerTags":21725,"PlayerTrack":51713,"PrefPro":15455,"PriceCheck":107876,"QoLBar":58100,"Quest Map":6228,"QuestAWAY":18404,"QuoteOfTheLobby":1456,"ReadyCheckHelper":15147,"Redirect":2918,"RemindMe":30400,"RemotePartyFinder":613,"RepairMe":39198,"Reset enmity command":2523,"RezPls":69028,"SillyChat":2262,"SimpleTweaksPlugin":787238,"SkillSwap":2029,"SlideCast":46934,"Snooper":386,"SonarPlugin":96917,"SoundFilter":10935,"SoundSetter":21984,"TPie":36755,"TeleporterPlugin":71317,"TextBoxStyler":10766,"TextToTalk":20082,"TheGreatSeparator":32061,"TheHeartOfTheParty":113,"TidyChat":18531,"Tippy":320,"TitleEdit":36357,"Tourist":45708,"TriadBuddy":18567,"VFXEditor":26369,"Visibility":61971,"VoidList":748,"Waitingway.Dalamud":4178,"WaymarkPresetPlugin":53491,"Weatherman":1005,"WheresWOLdo":9202,"WinTitle":677,"WondrousTailsSolver":183338,"Wordsmith":3480,"XIVChat":5643,"XIVCombo":177450,"XIVLogger":3267,"ZodiacBuddy":26377,"cl_showpos":504,"faderPlugin":24308,"orchestrion":148060,"owofy":37503,"ACTEndcounter":22,"AdaptiveHud":29,"AetherCompass":1252,"AutoTranslateXIV":130,"BatteryGauge":50,"BlueMageHelper":4846,"CharSyncPlugin":13,"CharacterPanelRefined":6298,"ChatEmoteColor":1021,"ChatTranslator":4547,"Dalamud.CharacterSync":50776,"EldenRing":1241,"FantasyPlayer.Dalamud":3177,"GearsetHelperPlugin":279,"HUDManager":12315,"HidePadlock":1159,"HuntBuddy":6063,"ItemVendorLocation":6251,"MPTimer":16,"MountCollectioner":481,"MouseTargetTooltip":659,"NextUIPlugin":1867,"NoKillPlugin":5686,"OBSPlugin":308,"OceanFishin":6697,"PartyListLayout":11570,"ProperHousing":174,"ResLogger2.Plugin":478,"ResetAudio":195,"SideHUDPlugin":834,"SimpleCompare":2444,"SizeMattersFishing":475,"SkillDisplay":138,"SupineSnail.JobGaugeAdjustments":2086,"TabTab":16,"WhatDidYouSay":204,"WhereAmIAgain":3917,"XIVDeck.FFXIVPlugin":881,"autoSweep":14482}