{"Accountant":73704,"AccurateCountDown":28843,"AdaptiveHud":736,"AdventurerInNeed":39959,"BetterPartyFinder":29573,"BigPlayerDebuffs":20863,"BrowserHost.Plugin":11530,"Browsingway":10530,"BurntToast":13143,"ChatAlerts":4783,"ChatBubbles":198876,"ChatCoordinates":37989,"ChatExtender":2679,"ChatTyper":2783,"ChillFrames":8144,"Compass":20953,"CurrencyAlert":8170,"DailyDuty":200800,"Dalamud.DiscordBridge":47569,"Dalamud.FindAnything":34570,"Dalamud.FullscreenCutscenes":876,"Dalamud.LoadingImage":96667,"Dalamud.RichPresence":97351,"DalamudVox":55,"DamageInfoPlugin":153449,"DeathRecap":44773,"DeepDungeonDex":53014,"DelvUI":158070,"DeviceChangeFix":4594,"EasyEyes":20710,"Echoglossian":16395,"EnemyListDebuffs":32247,"EngageTimer":151582,"ExpandedSearchInfo":27024,"FCNameColor":73194,"FPSPlugin":144397,"FauxHollowsSolver":49876,"FlashOnTell":17805,"FlyTextFilter":3583,"FullscreenToggle":2,"GatherBuddy":385693,"GentleTouch":3604,"Glamaholic":19260,"Globetrotter":127675,"GoodMemory":114915,"HarpHero":29775,"Housemate":35436,"InventoryTools":50936,"ItemSearchPlugin":158913,"JobBars":186095,"JobIcons":25913,"JustBackup":13962,"Kapture":58763,"KingdomHeartsPlugin":7730,"MOAction":61976,"MPTickBar":26046,"MacroChain":11168,"MapLinker":30001,"MarketBoardPlugin":179167,"Mini":7238,"MiniCactpotSolver":157618,"NamePlateDebuffs":9644,"Namingway":3557,"NeatNoter":70995,"NoSoliciting":57415,"NoTankYou":158978,"NotificationMaster":7133,"OopsAllLalafells":55231,"PartyIcons":51177,"PatMe":28265,"PeepingTom":155859,"PennyPincher":165403,"PingPlugin":435717,"PixelPerfect":131138,"PlayerTags":21726,"PlayerTrack":59122,"PrefPro":16289,"PriceCheck":131641,"QoLBar":69903,"Quest Map":8638,"QuestAWAY":24527,"QuoteOfTheLobby":1901,"ReadyCheckHelper":24696,"Redirect":5573,"RemindMe":30400,"RemotePartyFinder":978,"RepairMe":53234,"Reset enmity command":2523,"RezPls":72801,"SillyChat":2653,"SimpleTweaksPlugin":1000890,"SkillSwap":2857,"SlideCast":46934,"Snooper":2205,"SonarPlugin":129827,"SoundFilter":11899,"SoundSetter":27549,"TPie":38509,"TeleporterPlugin":89752,"TextBoxStyler":11321,"TextToTalk":21627,"TheGreatSeparator":33527,"TheHeartOfTheParty":837,"TidyChat":30401,"Tippy":2827,"TitleEdit":38049,"Tourist":49637,"TriadBuddy":27531,"VFXEditor":27886,"Visibility":65220,"VoidList":748,"Waitingway.Dalamud":4762,"WaymarkPresetPlugin":69996,"Weatherman":3057,"WhatDidYouSay":2336,"WheresWOLdo":10737,"WinTitle":874,"WondrousTailsSolver":192781,"Wordsmith":4810,"XIVChat":5950,"XIVCombo":185148,"XIVDeck.FFXIVPlugin":3269,"XIVLogger":4457,"ZodiacBuddy":29779,"autoSweep":21053,"cl_showpos":2348,"faderPlugin":24315,"orchestrion":181536,"owofy":38791,"ACTEndcounter":29,"ARealmRecorded":1048,"AetherCompass":3036,"AutoTranslateXIV":793,"BatteryGauge":207,"BlueMageHelper":4855,"CharSyncPlugin":16,"CharacterPanelRefined":14694,"ChatEmoteColor":1021,"ChatTranslator":4548,"CrossUp":1820,"Dalamud.CharacterSync":53432,"DeathRoll":458,"Distance":1911,"EldenRing":2298,"FantasyPlayer.Dalamud":3549,"GearsetHelperPlugin":790,"HUDManager":13641,"HidePadlock":1161,"HuntBuddy":7656,"ItemVendorLocation":7374,"MBHistory":128,"MPTimer":16,"MountCollectioner":482,"MouseTargetTooltip":662,"NextUIPlugin":2466,"NoKillPlugin":6410,"OBSPlugin":552,"OceanFishin":6703,"PartyListLayout":13223,"ProperHousing":2071,"ResLogger2.Plugin":565,"ResetAudio":1357,"SideHUDPlugin":842,"SimpleCompare":2447,"SizeMattersFishing":477,"SkillDisplay":967,"SupineSnail.JobGaugeAdjustments":2743,"TabTab":20,"WhereAmIAgain":4654}