{"Dalamud.RichPresence":156072,"EasyEyes":29566,"MacroChain":56360,"TriadBuddy":121301,"TargetFurniture":4857,"TidyChat":52380,"FlyTextFilter":15815,"Kapture":72926,"VFXEditor":47088,"DailyDuty":472734,"BetterPlaytime":6277,"AdaptiveHud":3824,"HuntHelper":7141,"owofy":44753,"ZodiacBuddy":120936,"FauxHollowsSolver":101686,"Housemate":52758,"WinTitle":1841,"SoundSetter":43738,"WheresWOLdo":17720,"ItemVendorLocation":20134,"NeatNoter":88562,"HuntBuddy":28097,"SkillSwap":6546,"TitleEdit":58467,"BurntToast":18091,"EngageTimer":299113,"XIVCombo":327413,"ResLogger2.Plugin":1004,"DeathRoll":4411,"Snooper":7789,"HarpHero":42773,"AutoMammet":3625,"Dalamud.LoadingImage":143368,"WaymarkPresetPlugin":181211,"PlayerTags":66544,"WhatDidYouSay":11356,"PixelPerfect":179532,"Dalamud.DiscordBridge":64548,"Wordsmith":22241,"FCNameColor":106451,"PatMe":54734,"TheHeartOfTheParty":5410,"QoLBar":98946,"Glamaholic":93819,"MOAction":99521,"TextToTalk":27370,"Globetrotter":210315,"Stormtalons":461,"BetterMountRoulette":1756,"Echoglossian":22380,"Distance":22355,"GoodFriend":7197,"Browsingway":22519,"WondrousTailsSolver":340093,"Accountant":129837,"Tippy":7950,"Visibility":99259,"PlayerTrack":94998,"DeepDungeonDex":181830,"MPTickBar":41228,"DelvUI":245972,"PartyIcons":113261,"JustBackup":42010,"Dalamud.FullscreenCutscenes":5251,"RepairMe":89177,"PrefPro":21918,"PriceInsight":26332,"PingPlugin":548213,"FlashOnTell":34601,"ItemSearchPlugin":199711,"ChatTyper":3838,"ChatAlerts":10336,"ChatCoordinates":53827,"DeathRecap":121853,"QuestMap":3578,"BetterPartyFinder":41194,"DeviceChangeFix":17557,"TeleporterPlugin":136363,"CharacterPanelRefined":90910,"WhereAmIAgain":9657,"PriceCheck":178365,"MapLinker":51395,"PeepingTom":285605,"FaderPlugin":255,"orchestrion":301631,"NoTankYou":286340,"Ffxiv2Mqtt":386,"MBHistory":1013,"ReSanctuary":46787,"ChillFrames":32024,"MarketBoardPlugin":472362,"RezPls":104780,"OrangeGuidanceTomestone":10329,"StackSellPrice":6302,"TextBoxStyler":14118,"CurrencyAlert":18386,"Redirect":18179,"EnemyListDebuffs":54694,"RemotePartyFinder":4212,"Tourist":96519,"MiniCactpotSolver":250154,"ExtraChat":4584,"ChatBubbles":362355,"GatherBuddy":670467,"Dalamud.CharacterSync":69420,"XIVDeck.FFXIVPlugin":10179,"XIVChat":7351,"cl_showpos":6076,"NoSoliciting":79479,"ReadyCheckHelper":42191,"TPie":57951,"TheGreatSeparator":46450,"Neko":13774,"Compass":32507,"XIVLogger":10712,"BigPlayerDebuffs":95044,"Messenger":3525,"Namingway":9608,"DamageInfoPlugin":224436,"Weatherman":17966,"Dalamud.FindAnything":48221,"ExpandedSearchInfo":41368,"InventoryTools":131750,"AdventurerInNeed":56856,"FPSPlugin":191019,"ChatTwo":49444,"SillyChat":4976,"GentleTouch":4805,"PennyPincher":255303,"SoundFilter":17583,"EnmityHp":11126,"JobBars":274864,"WhichPatchWasThat":2048,"SimpleTweaksPlugin":1701357,"GearsetHelperPlugin":2660,"CrossUp":4169,"HighFpsPhysicsPlugin":5253,"ARealmRecorded":4400,"OBSPlugin":1331,"TheDot":583,"AetherCompass":12755,"AbilityAnts":2071,"WhereIsMyMouse":1282,"CollectorsAnxiety":2675,"InventorySearchBar":5059,"ShowGear":159,"NoKillPlugin":9500,"HimbeertoniRaidTool":859,"EurekaTrackerAutoPopper":684,"PartyListLayout":19557,"KikoGuide":6140,"HUDManager":22561,"MiniMappingway":7255,"Tilted":709,"CoinPouch":1513,"UsedName":36,"QuestAWAY":32405,"ProperHousing":5758,"KitchenSync":158,"AccurateCountDown":28850,"AudibleCharacterStatus":10647,"BrowserHost.Plugin":11536,"ChatExtender":2685,"DalamudVox":57,"FullscreenToggle":12,"GoodMemory":114926,"JobIcons":25916,"KingdomHeartsPlugin":14936,"MimicryHelper":6674,"Mini":14883,"NamePlateDebuffs":11594,"NotificationMaster":14589,"OopsAllLalafells":55235,"Quest Map":978,"QuoteOfTheLobby":2674,"RemindMe":30402,"Reset enmity command":763,"SlideCast":46937,"SonarPlugin":214059,"VoidList":750,"Waitingway.Dalamud":6184,"autoSweep":40729,"faderPlugin":33944,"ACTEndcounter":38,"AutoTranslateXIV":1508,"BatteryGauge":433,"BlueMageHelper":4869,"CharSyncPlugin":23,"ChatEmoteColor":1025,"ChatTranslator":4554,"DomanMahjongStatus":141,"EldenRing":3104,"FantasyPlayer.Dalamud":4130,"HidePadlock":1168,"MPTimer":19,"MountCollectioner":488,"MouseTargetTooltip":667,"NextUIPlugin":3334,"OceanFishin":6707,"OhGeeCD":1252,"ResetAudio":2510,"SideHUDPlugin":846,"SimpleCompare":2452,"SizeMattersFishing":482,"SkillDisplay":1880,"SupineSnail.JobGaugeAdjustments":3644,"TabTab":24}