{"Dalamud.RichPresence":233985,"FPSPlugin":282557,"Dalamud.FullscreenCutscenes":11703,"InventorySearchBar":49762,"Waitingway.Dalamud":11461,"MPTickBar":53236,"PingPlugin":773577,"ActionTimeline":21493,"EnmityHp":62986,"ExtraChat":14244,"FaderPlugin":14842,"NeatNoter":112289,"HimbeertoniRaidTool":38132,"AbilityAnts":16896,"VFXEditor":200227,"PartyPlanner":4986,"SkillSwap":12458,"BurntToast":23872,"ZodiacBuddy":190716,"TitleEdit":90608,"ResizableHUD":3198,"Wordsmith":71792,"MiniCactpotSolver":386148,"Messenger":31647,"CharacterPanelRefined":414591,"KitchenSync":65512,"NextUIPlugin":8167,"PositionalGuide":13160,"ClarityInChaos":5733,"TeleporterPlugin":178949,"FlashOnTell":55468,"WinTitle":3721,"DamageInfoPlugin":380544,"WaymarkPresetPlugin":316729,"SonarPlugin":356738,"AutoMammet":25310,"TargetLines":3348,"DutyTracker":4460,"TheHeartOfTheParty":6193,"RemotePartyFinder":8765,"WhereAmIAgain":55808,"DeathRecap":315270,"WhatDidYouSay":20321,"Echoglossian":34367,"DelvUI":350870,"Visibility":205699,"PlayerTags":136478,"PlayerTrack":121223,"MemoryMarker":7577,"OrangeGuidanceTomestone":36610,"Dalamud.DiscordBridge":95026,"XIVDeck.FFXIVPlugin":24752,"CurrencyAlert":45040,"PrefPro":30278,"SoundSetter":72331,"Redirect":40821,"StackSellPrice":14244,"Mini":29794,"BetterMountRoulette":31469,"WondrousTailsSolver":506193,"Namingway":17184,"MarketBoardPlugin":683249,"Tourist":138552,"RoleplayProfiles":1560,"BetterShadows":39371,"TextToTalk":44941,"GatherBuddy":1308671,"BigPlayerDebuffs":162125,"FlyTextFilter":34262,"MiniMappingway":104391,"XIVChat":10570,"DeviceChangeFix":34805,"PriceInsight":288138,"ReSanctuary":106188,"PriceCheck":267382,"HuntBuddy":83662,"OBSPlugin":3566,"Accountant":221956,"Globetrotter":331911,"NoSoliciting":112268,"Tf2CriticalHitsPlugin":13759,"Congratulations":11011,"Tf2Hud":1395,"owofy":52108,"DailyDuty":1048405,"NotificationMaster":21181,"XIVCombo":426649,"Fungah":7105,"Browsingway":50598,"ChillFrames":76639,"PennyPincher":402433,"MonsterLootHunter":37362,"NamePlateDebuffs":43509,"Distance":47040,"BlueMageHelper":80900,"NOTED":8446,"ChatTwo":99742,"HuntHelper":75318,"ChatTyper":4880,"KingdomHeartsPlugin":22966,"Doorbell":9531,"WhichPatchWasThat":31023,"MacroChain":99677,"BetterPlaytime":56659,"cl_showpos":9656,"QoLBar":129101,"EmoteLog":10890,"ResLogger2.Plugin":3060,"TitleRoulette":1276,"SoundFilter":25888,"HarpHero":67909,"MimicryHelper":16301,"InventoryTools":461896,"WheresWOLdo":25346,"AudibleCharacterStatus":18546,"JobBars":398540,"GoodFriend":51710,"autoSweep":73628,"Dalamud.CharacterSync":114534,"LogogramHelper":10690,"RepairMe":117599,"ReadyCheckHelper":85726,"EurekaTrackerAutoPopper":63550,"PartyIcons":219378,"EurekaHelper":65541,"DeathRoll":18107,"MarketUploader":2679,"AdventurerInNeed":94299,"PeepingTom":482446,"QuestAWAY":44234,"HybridCamera":4451,"XIVLogger":20271,"CrossUp":10675,"Hunty":51954,"TPie":79418,"MBHistory":3052,"ChatBubbles":640818,"FauxHollowsSolver":164723,"DeepDungeonDex":470272,"ChatCoordinates":75056,"PatMe":134032,"BatteryGauge":3180,"SillyChat":7998,"ItemSearchPlugin":279290,"PushyFinder":925,"MOAction":137138,"SubmarineTracker":30104,"JustBackup":86098,"TextBoxStyler":15101,"Wholist":16027,"ChatAlerts":18792,"Dalamud.LoadingImage":221520,"Stormtalons":1732,"Compass":43336,"Dalamud.FindAnything":72390,"TriadBuddy":326662,"ExpandedSearchInfo":53523,"QuestMap":18259,"Housemate":88130,"Tilted":9338,"ItemVendorLocation":143890,"orchestrion":548268,"RezPls":145766,"Honorific":115372,"EasyEyes":51512,"WorkshopOptimizerPlugin":23187,"Neko":51033,"FCNameColor":222419,"Glamaholic":196104,"AdaptiveHud":7648,"MacroRecorded":1116,"TheGreatSeparator":54774,"PixelPerfect":333561,"GentleTouch":9335,"MapLinker":67721,"Tippy":13817,"Snooper":17884,"Kapture":90697,"EnemyListDebuffs":116210,"BetterPartyFinder":44621,"UsedName":4643,"TooltipNotes":1271,"StanleyParableXiv":6021,"ARealmRecorded":18714,"Weatherman":50153,"SimpleTweaksPlugin":3141514,"TidyChat":72654,"Ffxiv2Mqtt":886,"BozjaBuddy":23232,"NoTankYou":416750,"DeepDungeonTracker":26616,"EngageTimer":416877,"TargetFurniture":22842,"G4EUkrChatSupport":101,"HUDManager":36536,"Beachcomber":61680,"AetherCompass":25982,"xivr":16128,"OofPlugin":3702,"CollectorsAnxiety":14143,"CameraLoader":826,"KikoGuide":10163,"borderless-fix":1070,"HighFpsPhysicsPlugin":23276,"SimpleCompare":3852,"ChatEmoteColor":2422,"SelfCare":1439,"ShowGear":1084,"DaCoblyn":1572,"XIVWindowResizer":2032,"CoinPouch":2169,"ProperHousing":15814,"NoKillPlugin":12297,"PartyListLayout":20880,"TheDot":1174,"EldenRing":4941,"GearsetHelperPlugin":3105,"VanillaHotbarExtender":1068,"Linkpearl":119,"BetterTargetingSystem":4106,"CollectableCalculator":1905,"rtyping":2448,"TwitchXIV":308,"Mappy":2555,"WhereIsMyMouse":5105,"RPBlurb":1468,"FantasyPlayer":746,"OceanFishin":12459,"WhosTalking":2104,"QuoteOfTheLobby":3479,"FFXIVRPCalendarPlugin":131,"AccurateCountDown":28862,"BrowserHost.Plugin":11545,"ChatExtender":2695,"DalamudVox":69,"FullscreenToggle":26,"GoodMemory":114941,"JobIcons":25925,"OopsAllLalafells":55248,"Quest Map":986,"RemindMe":30413,"Reset enmity command":771,"SlideCast":46951,"VoidList":759,"ACTEndcounter":49,"AutoTranslateXIV":1525,"CharSyncPlugin":35,"ChatTranslator":4566,"DomanMahjongStatus":154,"FantasyPlayer.Dalamud":4148,"HidePadlock":1180,"MPTimer":33,"MountCollectioner":505,"MouseTargetTooltip":681,"OhGeeCD":1266,"ResetAudio":2524,"SideHUDPlugin":858,"SizeMattersFishing":498,"SkillDisplay":1894,"SupineSnail.JobGaugeAdjustments":3657,"TabTab":45}