{"Dalamud.RichPresence":156810,"AutoMammet":4227,"FauxHollowsSolver":102319,"EasyEyes":29786,"MacroChain":56821,"TriadBuddy":122291,"TargetFurniture":4992,"TidyChat":52670,"FlyTextFilter":15899,"Kapture":73211,"VFXEditor":47309,"DailyDuty":496532,"BetterPlaytime":8733,"AdaptiveHud":3916,"HuntHelper":7671,"Snooper":7885,"owofy":44866,"Housemate":52962,"HarpHero":43020,"WinTitle":1867,"SoundSetter":43942,"WheresWOLdo":17842,"ItemVendorLocation":20622,"NeatNoter":88848,"HuntBuddy":28667,"SkillSwap":6640,"TitleEdit":58657,"BurntToast":18217,"EngageTimer":300659,"XIVCombo":328771,"ResLogger2.Plugin":1019,"ZodiacBuddy":121488,"DeathRoll":4514,"Dalamud.LoadingImage":144659,"Echoglossian":22552,"Stormtalons":487,"Globetrotter":211558,"TextToTalk":27450,"MOAction":103416,"Glamaholic":94482,"QoLBar":104790,"PatMe":55174,"PriceInsight":28730,"FCNameColor":107174,"Wordsmith":22629,"Dalamud.DiscordBridge":65100,"PixelPerfect":180467,"WhatDidYouSay":11489,"PlayerTags":68074,"RepairMe":89510,"WaymarkPresetPlugin":182774,"Distance":22642,"BetterMountRoulette":2142,"Dalamud.FullscreenCutscenes":5313,"JustBackup":42377,"PartyIcons":113824,"DelvUI":248973,"MPTickBar":41666,"PrefPro":22020,"DeepDungeonDex":182674,"Visibility":99643,"Tippy":8525,"Accountant":130370,"WondrousTailsSolver":349050,"Browsingway":24761,"GoodFriend":8100,"PlayerTrack":95752,"ChatTwo":50126,"PingPlugin":549634,"TPie":62583,"ChatAlerts":10430,"ChatCoordinates":54068,"DeathRecap":122824,"QuestMap":3831,"BetterPartyFinder":41487,"DeviceChangeFix":17809,"TeleporterPlugin":136916,"CharacterPanelRefined":92517,"WhereAmIAgain":9888,"PriceCheck":178849,"MapLinker":52611,"PeepingTom":287240,"FaderPlugin":373,"orchestrion":302661,"NoTankYou":295936,"Ffxiv2Mqtt":422,"MBHistory":1042,"ReSanctuary":53073,"ChillFrames":32254,"MarketBoardPlugin":474544,"RezPls":105239,"OrangeGuidanceTomestone":10958,"StackSellPrice":6368,"TextBoxStyler":14156,"CurrencyAlert":18730,"Redirect":18448,"EnemyListDebuffs":55115,"RemotePartyFinder":4296,"Tourist":97330,"FlashOnTell":34813,"ItemSearchPlugin":200412,"MiniCactpotSolver":252067,"Namingway":9693,"DamageInfoPlugin":225138,"Messenger":3794,"BigPlayerDebuffs":95983,"XIVLogger":10877,"Compass":32746,"Neko":16016,"TheGreatSeparator":46646,"ReadyCheckHelper":42621,"ChatTyper":3859,"NoSoliciting":79912,"cl_showpos":6154,"XIVChat":7384,"XIVDeck.FFXIVPlugin":10248,"Dalamud.CharacterSync":70287,"GatherBuddy":673266,"ExtraChat":4682,"ChatBubbles":365996,"Weatherman":18208,"TheHeartOfTheParty":5461,"WhichPatchWasThat":2306,"JobBars":275884,"EnmityHp":11546,"SoundFilter":17705,"PennyPincher":256177,"InventorySearchBar":6364,"GentleTouch":4850,"SimpleTweaksPlugin":1712525,"FPSPlugin":191881,"AdventurerInNeed":57307,"InventoryTools":132663,"ExpandedSearchInfo":41587,"Dalamud.FindAnything":48350,"SillyChat":5029,"NextUIPlugin":3626,"HighFpsPhysicsPlugin":5321,"ARealmRecorded":4956,"OBSPlugin":1344,"GearsetHelperPlugin":2690,"CrossUp":4213,"WhereIsMyMouse":1337,"CollectorsAnxiety":2757,"ShowGear":177,"NoKillPlugin":9566,"TheDot":618,"AetherCompass":14643,"AbilityAnts":2222,"ProperHousing":6438,"EurekaTrackerAutoPopper":755,"PartyListLayout":19650,"KikoGuide":6215,"HUDManager":22707,"HimbeertoniRaidTool":1309,"UsedName":126,"QuestAWAY":32473,"MiniMappingway":11532,"Tilted":734,"CoinPouch":1557,"KitchenSync":1323,"AccurateCountDown":28850,"AudibleCharacterStatus":10831,"BrowserHost.Plugin":11536,"ChatExtender":2685,"DalamudVox":57,"FullscreenToggle":12,"GoodMemory":114926,"JobIcons":25916,"KingdomHeartsPlugin":15074,"MimicryHelper":6816,"Mini":15003,"NamePlateDebuffs":11594,"NotificationMaster":14680,"OopsAllLalafells":55235,"Quest Map":978,"QuoteOfTheLobby":2674,"RemindMe":30402,"Reset enmity command":763,"SlideCast":46937,"SonarPlugin":214903,"VoidList":750,"Waitingway.Dalamud":6184,"autoSweep":41096,"faderPlugin":34172,"ACTEndcounter":38,"AutoTranslateXIV":1508,"BatteryGauge":433,"BlueMageHelper":4869,"CharSyncPlugin":23,"ChatEmoteColor":1025,"ChatTranslator":4554,"DomanMahjongStatus":141,"EldenRing":3104,"FantasyPlayer.Dalamud":4130,"HidePadlock":1168,"MPTimer":19,"MountCollectioner":488,"MouseTargetTooltip":667,"OceanFishin":6707,"OhGeeCD":1253,"ResetAudio":2510,"SideHUDPlugin":846,"SimpleCompare":2452,"SizeMattersFishing":482,"SkillDisplay":1880,"SupineSnail.JobGaugeAdjustments":3644,"TabTab":24}