{"Dalamud.RichPresence":185568,"XIVCombo":340372,"ResLogger2.Plugin":1363,"Housemate":55378,"Snooper":9298,"TitleEdit":60684,"BurntToast":19340,"EngageTimer":310654,"InventorySearchBar":14666,"Accountant":135467,"HuntHelper":12790,"SkillSwap":7588,"FlyTextFilter":16700,"owofy":45859,"Stormtalons":707,"TargetFurniture":6618,"ExpandedSearchInfo":43587,"InventoryTools":158982,"FauxHollowsSolver":108014,"Compass":34970,"NoTankYou":337226,"FaderPlugin":1409,"MapLinker":55130,"MBHistory":1398,"XIVDeck.FFXIVPlugin":13014,"Neko":33405,"VFXEditor":65473,"DailyDuty":645476,"JobBars":283706,"Kapture":75573,"NeatNoter":91498,"DeathRoll":6551,"AdaptiveHud":4843,"BetterPlaytime":18347,"TheGreatSeparator":48512,"WhatDidYouSay":12501,"BetterMountRoulette":7752,"Distance":25518,"WondrousTailsSolver":369420,"PrefPro":23076,"Visibility":110519,"ItemVendorLocation":25362,"PixelPerfect":189064,"PlayerTrack":98858,"Dalamud.DiscordBridge":68318,"Browsingway":29132,"ChatTwo":56652,"WinTitle":2066,"DeepDungeonDex":237506,"WheresWOLdo":18977,"TPie":69509,"MPTickBar":43928,"RepairMe":92940,"Wordsmith":41391,"DelvUI":265894,"ZodiacBuddy":126348,"TriadBuddy":166946,"GoodFriend":26136,"EasyEyes":31749,"TheHeartOfTheParty":5952,"AutoMammet":9439,"Dalamud.LoadingImage":155765,"NextUIPlugin":5122,"MacroChain":61082,"UsedName":818,"WhichPatchWasThat":7462,"FPSPlugin":200629,"KitchenSync":26788,"MiniCactpotSolver":269267,"TidyChat":55336,"EnmityHp":17106,"JustBackup":46059,"GatherBuddy":776902,"NamePlateDebuffs":17159,"PlayerTags":91787,"HarpHero":45725,"SoundSetter":45468,"PriceInsight":78532,"HuntBuddy":34388,"PatMe":73678,"PingPlugin":562088,"MarketBoardPlugin":495808,"Tourist":104070,"Glamaholic":101449,"CurrencyAlert":21170,"StackSellPrice":7082,"TextBoxStyler":14564,"ReSanctuary":62485,"ChillFrames":44679,"RemotePartyFinder":4968,"WaymarkPresetPlugin":190229,"QoLBar":110392,"Globetrotter":224712,"QuestMap":6421,"DeathRecap":158633,"ChatCoordinates":56763,"WhereAmIAgain":12614,"TeleporterPlugin":142156,"DeviceChangeFix":20166,"FlashOnTell":37135,"HimbeertoniRaidTool":10551,"PeepingTom":304712,"ItemSearchPlugin":206852,"OrangeGuidanceTomestone":14702,"SillyChat":5452,"CharacterPanelRefined":194481,"RoleplayProfiles":404,"Echoglossian":24297,"PartyIcons":162202,"cl_showpos":6885,"Tilted":1691,"NoSoliciting":83891,"EnemyListDebuffs":59839,"DamageInfoPlugin":231380,"TextToTalk":28806,"FCNameColor":113493,"PriceCheck":213934,"Namingway":10720,"Redirect":20994,"RezPls":109614,"ActionTimeline":4384,"MOAction":108558,"Tippy":9666,"BetterPartyFinder":43754,"Dalamud.FullscreenCutscenes":6161,"SoundFilter":18914,"Weatherman":21177,"ChatBubbles":393280,"ChatTyper":4046,"SimpleTweaksPlugin":1926028,"ChatAlerts":11639,"MiniMappingway":28185,"ReadyCheckHelper":45382,"AdventurerInNeed":61667,"Dalamud.CharacterSync":78370,"GentleTouch":5228,"Messenger":10848,"XIVChat":7758,"BigPlayerDebuffs":104425,"ExtraChat":5738,"orchestrion":344666,"Dalamud.FindAnything":53223,"PennyPincher":265284,"Ffxiv2Mqtt":538,"XIVLogger":12482,"Waitingway.Dalamud":7210,"CollectorsAnxiety":5640,"CrossUp":4631,"KikoGuide":9703,"NOTED":531,"AetherCompass":17591,"AbilityAnts":3453,"OofPlugin":246,"ShowGear":358,"BetterShadows":1438,"xivr":8480,"DutyTracker":193,"GearsetHelperPlugin":2978,"WhereIsMyMouse":1989,"WorkshopOptimizerPlugin":1654,"NoKillPlugin":10296,"Mappy":370,"ProperHousing":7988,"HighFpsPhysicsPlugin":9435,"ARealmRecorded":6695,"OBSPlugin":1504,"QuestAWAY":33490,"TheDot":1033,"EurekaTrackerAutoPopper":1614,"Beachcomber":15673,"PartyListLayout":20550,"VanillaHotbarExtender":241,"HUDManager":24101,"PartyPlanner":70,"CoinPouch":1997,"DeepDungeonTracker":94,"AccurateCountDown":28852,"AudibleCharacterStatus":12451,"BrowserHost.Plugin":11536,"ChatExtender":2685,"DalamudVox":61,"FullscreenToggle":17,"GoodMemory":114926,"JobIcons":25918,"KingdomHeartsPlugin":16503,"MimicryHelper":8055,"Mini":16302,"NotificationMaster":15499,"OopsAllLalafells":55237,"Quest Map":979,"QuoteOfTheLobby":2677,"RemindMe":30406,"Reset enmity command":763,"SlideCast":46937,"SonarPlugin":246970,"VoidList":751,"autoSweep":45890,"faderPlugin":36424,"ACTEndcounter":38,"AutoTranslateXIV":1512,"BatteryGauge":438,"BlueMageHelper":4871,"CharSyncPlugin":23,"ChatEmoteColor":1026,"ChatTranslator":4554,"DomanMahjongStatus":141,"EldenRing":3106,"FantasyPlayer.Dalamud":4132,"HidePadlock":1169,"MPTimer":20,"MountCollectioner":492,"MouseTargetTooltip":668,"OceanFishin":6707,"OhGeeCD":1254,"ResetAudio":2510,"SideHUDPlugin":846,"SimpleCompare":2452,"SizeMattersFishing":484,"SkillDisplay":1882,"SupineSnail.JobGaugeAdjustments":3645,"TabTab":29}