{"AccurateCountDown":{"count":9416},"AdventurerInNeed":{"count":4981},"AetherSense":{"count":2760},"BetterPartyFinder":{"count":120},"BrowserHost.Plugin":{"count":4996},"ChatCoordinates":{"count":4110},"ChatExtender":{"count":2633},"Dalamud.CharacterSync":{"count":6621},"Dalamud.DiscordBridge":{"count":4406},"Dalamud.RichPresence":{"count":9300},"DalamudVox":{"count":24},"DamageInfoPlugin":{"count":13619},"ExpandedSearchInfo":{"count":135},"FPSPlugin":{"count":10864},"GatherBuddy":{"count":203},"Globetrotter":{"count":14645},"GoodMemory":{"count":9879},"Housemate":{"count":145},"HudSwap":{"count":2830},"ItemSearchPlugin":{"count":13463},"JobIcons":{"count":8521},"Kapture":{"count":231},"MOAction":{"count":10971},"MacroRecursion":{"count":5804},"MapLinker":{"count":4396},"MarketBoardPlugin":{"count":15360},"NeatNoter":{"count":4313},"NoSoliciting":{"count":17128},"OopsAllLalafells":{"count":4173},"PeepingTom":{"count":15527},"PennyPincher":{"count":11024},"PingPlugin":{"count":12820},"PixelPerfect":{"count":12360},"PlayerTrack":{"count":99},"PrefPro":{"count":2312},"PriceCheck":{"count":13325},"QoLBar":{"count":5793},"RemindMe":{"count":8145},"SimpleTweaksPlugin":{"count":8763},"SlideCast":{"count":14663},"SoundSetter":{"count":4477},"TeleporterPlugin":{"count":10139},"TextToTalk":{"count":1318},"TitleEdit":{"count":3605},"Tourist":{"count":238},"VFXEditor":{"count":100},"Visibility":{"count":3967},"VoidList":{"count":742},"WOLdo":{"count":65},"WaymarkPresetPlugin":{"count":4195},"XIVChat":{"count":1730},"XIVCombo":{"count":10259},"autoSweep":{"count":221},"orchestrion":{"count":7149},"owofy":{"count":22417}}