{"AccurateCountDown":{"count":998},"AdventurerInNeed":{"count":314},"BrowserHost.Plugin":{"count":1858},"ChatCoordinates":{"count":394},"ChatExtender":{"count":759},"Dalamud.CharacterSync":{"count":546},"Dalamud.RichPresence":{"count":771},"DamageInfoPlugin":{"count":3411},"FPSPlugin":{"count":1925},"Globetrotter":{"count":4103},"GoodMemory":{"count":378},"HudSwap":{"count":328},"ItemSearchPlugin":{"count":5913},"MOAction":{"count":4254},"MacroRecursion":{"count":1262},"MapLinker":{"count":609},"MarketBoardPlugin":{"count":1248},"NeatNoter":{"count":314},"NoSoliciting":{"count":5296},"PeepingTom":{"count":3997},"PennyPincher":{"count":2634},"PingPlugin":{"count":2802},"PixelPerfect":{"count":1032},"PriceCheck":{"count":422},"SlideCast":{"count":1100},"SoundSetter":{"count":1520},"TeleporterPlugin":{"count":4447},"TitleEdit":{"count":86},"VoidList":{"count":324},"WaymarkPresetPlugin":{"count":353},"XIVCombo":{"count":892},"orchestrion":{"count":830},"owofy":{"count":10065}}