{"AccurateCountDown":{"count":4380},"AdventurerInNeed":{"count":3074},"BrowserHost.Plugin":{"count":3337},"ChatCoordinates":{"count":1558},"ChatExtender":{"count":2630},"Dalamud.CharacterSync":{"count":2951},"Dalamud.DiscordBridge":{"count":1410},"Dalamud.RichPresence":{"count":4313},"DalamudVox":{"count":24},"DamageInfoPlugin":{"count":8090},"FPSPlugin":{"count":5662},"Globetrotter":{"count":8348},"GoodMemory":{"count":4300},"HudSwap":{"count":1529},"ItemSearchPlugin":{"count":9379},"JobIcons":{"count":3882},"MOAction":{"count":6792},"MacroRecursion":{"count":3212},"MapLinker":{"count":2444},"MarketBoardPlugin":{"count":5694},"NeatNoter":{"count":2309},"NoSoliciting":{"count":10509},"PeepingTom":{"count":7982},"PennyPincher":{"count":6552},"PingPlugin":{"count":6747},"PixelPerfect":{"count":5593},"PrefPro":{"count":1211},"PriceCheck":{"count":6972},"RemindMe":{"count":2423},"SimpleTweaksPlugin":{"count":533},"SlideCast":{"count":6463},"SoundSetter":{"count":2998},"TeleporterPlugin":{"count":6792},"TextToTalk":{"count":440},"TitleEdit":{"count":103},"Visibility":{"count":900},"VoidList":{"count":742},"WaymarkPresetPlugin":{"count":1871},"XIVChat":{"count":949},"XIVCombo":{"count":4684},"orchestrion":{"count":3323},"owofy":{"count":19663}}