{"Dalamud.RichPresence":226499,"GentleTouch":8394,"InventoryTools":314410,"Tilted":7840,"ExpandedSearchInfo":44464,"autoSweep":70074,"EngageTimer":408122,"JobBars":353537,"Dalamud.FindAnything":68915,"ChatTwo":84626,"AudibleCharacterStatus":16232,"ItemVendorLocation":115264,"ChatTyper":4677,"TargetFurniture":21084,"GoodFriend":36932,"AdventurerInNeed":80490,"SimpleTweaksPlugin":2825190,"MiniCactpotSolver":371008,"EasyEyes":45319,"Kapture":88246,"TheGreatSeparator":49384,"BetterPartyFinder":44617,"WhichPatchWasThat":22182,"Stormtalons":1502,"Neko":48657,"QoLBar":125761,"Ffxiv2Mqtt":792,"MimicryHelper":14646,"Dalamud.CharacterSync":107697,"Messenger":21435,"KingdomHeartsPlugin":21088,"AdaptiveHud":7069,"EnemyListDebuffs":91113,"Tippy":12976,"NOTED":6715,"Weatherman":36242,"FPSPlugin":272791,"MarketUploader":1355,"InventorySearchBar":38829,"ResLogger2.Plugin":2690,"SkillSwap":11505,"HuntHelper":60061,"BetterPlaytime":52452,"ChatBubbles":509483,"JustBackup":81585,"DeepDungeonDex":402736,"VFXEditor":116885,"HimbeertoniRaidTool":23948,"Wordsmith":69782,"NoSoliciting":107600,"AbilityAnts":13333,"PlayerTrack":111189,"Compass":41576,"cl_showpos":8972,"ActionTimeline":15438,"PixelPerfect":321906,"TitleEdit":87342,"DailyDuty":932022,"NotificationMaster":20427,"Fungah":2416,"MPTickBar":51440,"ChillFrames":72404,"Visibility":164778,"Congratulations":6077,"Distance":37282,"WheresWOLdo":24447,"Namingway":16251,"MonsterLootHunter":21796,"owofy":50862,"NoTankYou":399445,"ChatAlerts":17676,"AutoMammet":15737,"PartyPlanner":2835,"PlayerTags":116261,"PingPlugin":657693,"Dalamud.FullscreenCutscenes":10853,"FaderPlugin":8416,"Waitingway.Dalamud":10665,"MapLinker":66311,"NextUIPlugin":6820,"Snooper":16383,"TidyChat":69885,"RezPls":141115,"ZodiacBuddy":181997,"MOAction":125399,"EnmityHp":57034,"UsedName":3850,"Accountant":202645,"EmoteLog":1714,"StanleyParableXiv":3269,"Hunty":20636,"BlueMageHelper":33051,"Globetrotter":317873,"SoundSetter":65127,"XIVChat":9360,"ReadyCheckHelper":70399,"BatteryGauge":2328,"CharacterPanelRefined":247816,"WaymarkPresetPlugin":289362,"KitchenSync":65507,"MemoryMarker":3336,"XIVCombo":392661,"DutyTracker":1897,"DelvUI":330595,"RemotePartyFinder":8069,"WondrousTailsSolver":494738,"PrefPro":29187,"PartyIcons":204701,"Dalamud.DiscordBridge":83039,"DeathRoll":14978,"CurrencyAlert":39542,"Browsingway":46358,"NamePlateDebuffs":33682,"WhatDidYouSay":19491,"WinTitle":3542,"RepairMe":113271,"PriceCheck":246273,"PriceInsight":201375,"OrangeGuidanceTomestone":33696,"StackSellPrice":11115,"PositionalGuide":6792,"BetterMountRoulette":24524,"TeleporterPlugin":173951,"DeathRecap":235528,"XIVDeck.FFXIVPlugin":22250,"TheHeartOfTheParty":6186,"ClarityInChaos":2027,"WhereAmIAgain":51622,"Echoglossian":30584,"PennyPincher":389134,"DamageInfoPlugin":338838,"ItemSearchPlugin":246677,"NeatNoter":109023,"ReSanctuary":97957,"Tourist":118099,"RoleplayProfiles":1326,"FlyTextFilter":31025,"SoundFilter":24730,"BigPlayerDebuffs":153927,"FauxHollowsSolver":157897,"GatherBuddy":1119132,"Mini":28327,"EurekaTrackerAutoPopper":27534,"MacroChain":93183,"EurekaHelper":12911,"BetterShadows":25091,"HarpHero":65089,"BurntToast":22710,"TPie":77821,"HuntBuddy":61516,"Redirect":31740,"TextToTalk":43049,"QuestMap":15910,"orchestrion":426424,"MarketBoardPlugin":611715,"QuestAWAY":41606,"ExtraChat":10351,"TooltipNotes":811,"OBSPlugin":3182,"PeepingTom":402094,"Housemate":73620,"PatMe":104467,"Dalamud.LoadingImage":186001,"SillyChat":7522,"DeviceChangeFix":32537,"XIVLogger":18835,"MiniMappingway":73834,"ChatCoordinates":72640,"FlashOnTell":53021,"WorkshopOptimizerPlugin":6852,"FCNameColor":201320,"LogogramHelper":3493,"Wholist":7319,"TitleRoulette":576,"TriadBuddy":309973,"Glamaholic":141561,"MBHistory":2623,"TextBoxStyler":14734,"Tf2CriticalHitsPlugin":7728,"Doorbell":3306,"DeepDungeonTracker":16774,"NoKillPlugin":10573,"ARealmRecorded":9288,"SelfCare":951,"ShowGear":884,"PartyListLayout":20876,"VanillaHotbarExtender":881,"GearsetHelperPlugin":3101,"EldenRing":4554,"HighFpsPhysicsPlugin":14847,"TargetLines":736,"ChatEmoteColor":1964,"DaCoblyn":984,"TheDot":1170,"BetterTargetingSystem":2378,"QuoteOfTheLobby":3242,"KikoGuide":10157,"BozjaBuddy":3580,"XIVWindowResizer":1377,"Beachcomber":40588,"PushyFinder":68,"AetherCompass":24096,"ProperHousing":12256,"Mappy":2545,"HUDManager":31510,"CoinPouch":2165,"HybridCamera":1361,"xivr":14922,"CrossUp":6805,"Linkpearl":19,"CollectableCalculator":190,"borderless-fix":579,"SimpleCompare":3462,"CollectorsAnxiety":8524,"OofPlugin":2232,"ResizableHUD":767,"MacroRecorded":42,"WhosTalking":226,"WhereIsMyMouse":4268,"rtyping":977,"OceanFishin":9349,"G4EUkrChatSupport":26,"SubmarineTracker":459,"Tf2Hud":12,"TwitchXIV":9,"AccurateCountDown":28857,"BrowserHost.Plugin":11541,"ChatExtender":2689,"DalamudVox":65,"FullscreenToggle":22,"GoodMemory":114935,"JobIcons":25922,"OopsAllLalafells":55244,"Quest Map":983,"RemindMe":30410,"Reset enmity command":768,"SlideCast":46948,"SonarPlugin":326148,"VoidList":756,"ACTEndcounter":46,"AutoTranslateXIV":1521,"CharSyncPlugin":32,"ChatTranslator":4562,"DomanMahjongStatus":149,"FantasyPlayer.Dalamud":4145,"HidePadlock":1177,"MPTimer":29,"MountCollectioner":500,"MouseTargetTooltip":677,"OhGeeCD":1263,"ResetAudio":2521,"SideHUDPlugin":855,"SizeMattersFishing":492,"SkillDisplay":1890,"SupineSnail.JobGaugeAdjustments":3654,"TabTab":40}