{"Dalamud.RichPresence":223164,"DeathRoll":12935,"DamageInfoPlugin":309864,"XIVChat":9221,"EurekaTrackerAutoPopper":7184,"PartyIcons":201801,"StackSellPrice":10761,"PriceInsight":166995,"SoundSetter":63665,"WinTitle":3008,"RepairMe":111397,"ItemSearchPlugin":244029,"RemotePartyFinder":7767,"NeatNoter":107698,"PriceCheck":244011,"OrangeGuidanceTomestone":32197,"BlueMageHelper":28155,"ReSanctuary":95444,"PositionalGuide":2258,"ReadyCheckHelper":69267,"WhatDidYouSay":19110,"NamePlateDebuffs":32178,"CharacterPanelRefined":241302,"Globetrotter":311689,"BetterMountRoulette":16831,"TitleRoulette":402,"Dalamud.DiscordBridge":81966,"Housemate":72298,"MemoryMarker":1731,"SillyChat":7339,"XIVCombo":387899,"MarketBoardPlugin":603117,"BatteryGauge":1898,"TeleporterPlugin":171514,"WaymarkPresetPlugin":286296,"DeathRecap":205909,"KitchenSync":63138,"TheHeartOfTheParty":6186,"Echoglossian":29534,"WhereAmIAgain":49199,"CurrencyAlert":37136,"DelvUI":327166,"EurekaHelper":6314,"ChatTyper":4586,"MacroChain":90662,"Wholist":5215,"FlashOnTell":51849,"TriadBuddy":261344,"FCNameColor":179852,"ChatCoordinates":71501,"Namingway":15473,"ExtraChat":9871,"Hunty":5784,"AbilityAnts":11865,"PlayerTrack":110302,"AutoMammet":15410,"HimbeertoniRaidTool":18622,"Glamaholic":138369,"PatMe":102244,"TextBoxStyler":14734,"MimicryHelper":14012,"EngageTimer":404371,"QuestMap":14788,"LogogramHelper":2289,"Dalamud.LoadingImage":160221,"PrefPro":28702,"MiniMappingway":69471,"RoleplayProfiles":1191,"BurntToast":22126,"Mini":27637,"FlyTextFilter":28755,"Tourist":106400,"Browsingway":41475,"Redirect":30663,"HuntBuddy":58686,"TPie":77103,"GatherBuddy":1066037,"orchestrion":421650,"QuestAWAY":40423,"TextToTalk":42290,"SoundFilter":24194,"BetterShadows":22878,"HarpHero":63703,"BigPlayerDebuffs":150467,"PennyPincher":381141,"Congratulations":3512,"ZodiacBuddy":156528,"ChatBubbles":499888,"JobBars":350244,"Dalamud.FullscreenCutscenes":10418,"ChatTwo":80440,"GoodFriend":36212,"AdaptiveHud":6819,"Neko":47604,"QoLBar":124331,"Tilted":7154,"FPSPlugin":268247,"BetterPartyFinder":44617,"EasyEyes":43533,"InventoryTools":274319,"NotificationMaster":20021,"ItemVendorLocation":66450,"UsedName":2581,"Messenger":19981,"SimpleTweaksPlugin":2562845,"Dalamud.FindAnything":59800,"ResLogger2.Plugin":2583,"InventorySearchBar":36469,"SkillSwap":11078,"autoSweep":68240,"Tippy":12538,"PlayerTags":114448,"HuntHelper":40344,"KingdomHeartsPlugin":20133,"GentleTouch":8126,"TargetFurniture":20247,"EnemyListDebuffs":87948,"BetterPlaytime":40262,"MiniCactpotSolver":363471,"TheGreatSeparator":49383,"Kapture":87183,"Dalamud.CharacterSync":105006,"ExpandedSearchInfo":44461,"Stormtalons":1408,"Weatherman":34729,"AdventurerInNeed":78731,"WhichPatchWasThat":21329,"NOTED":6180,"MarketUploader":846,"owofy":50305,"Waitingway.Dalamud":10334,"Accountant":188561,"DailyDuty":875160,"MOAction":123943,"TidyChat":68565,"JustBackup":79435,"Snooper":15757,"XIVDeck.FFXIVPlugin":21548,"RezPls":139028,"MBHistory":2469,"PartyPlanner":2575,"VFXEditor":100828,"NextUIPlugin":6152,"PingPlugin":618379,"Wordsmith":68802,"FaderPlugin":6317,"NoTankYou":390921,"EnmityHp":54413,"ChatAlerts":17152,"Distance":36237,"WheresWOLdo":23981,"Visibility":162407,"NoSoliciting":105373,"PixelPerfect":311914,"ActionTimeline":14118,"MPTickBar":50762,"ChillFrames":67956,"Tf2CriticalHitsPlugin":4440,"DeepDungeonDex":374048,"MapLinker":65611,"MonsterLootHunter":10901,"Compass":40694,"DeviceChangeFix":31529,"XIVLogger":18129,"PeepingTom":394448,"FauxHollowsSolver":154782,"cl_showpos":8690,"DutyTracker":1185,"WondrousTailsSolver":489134,"TitleEdit":79937,"OBSPlugin":3043,"WorkshopOptimizerPlugin":3647,"Fungah":349,"HybridCamera":941,"Mappy":2545,"AetherCompass":23385,"CoinPouch":2164,"StanleyParableXiv":1935,"GearsetHelperPlugin":3101,"ProperHousing":11777,"xivr":13030,"rtyping":694,"EldenRing":4399,"EmoteLog":223,"ResizableHUD":603,"OofPlugin":1993,"CollectorsAnxiety":7748,"SimpleCompare":3301,"borderless-fix":374,"WhereIsMyMouse":3883,"CrossUp":6539,"TooltipNotes":432,"Doorbell":1654,"Beachcomber":38598,"PartyListLayout":20876,"TargetLines":563,"VanillaHotbarExtender":803,"ChatEmoteColor":1812,"ShowGear":809,"SelfCare":782,"ARealmRecorded":8902,"NoKillPlugin":10573,"AudibleCharacterStatus":14759,"HighFpsPhysicsPlugin":14420,"DaCoblyn":594,"KikoGuide":10157,"XIVWindowResizer":1047,"TheDot":1170,"Ffxiv2Mqtt":739,"HUDManager":30663,"DeepDungeonTracker":9191,"QuoteOfTheLobby":3159,"BetterTargetingSystem":1671,"BozjaBuddy":491,"ClarityInChaos":568,"OceanFishin":7909,"AccurateCountDown":28857,"BrowserHost.Plugin":11541,"ChatExtender":2689,"DalamudVox":65,"FullscreenToggle":22,"GoodMemory":114935,"JobIcons":25922,"OopsAllLalafells":55243,"Quest Map":983,"RemindMe":30410,"Reset enmity command":768,"SlideCast":46948,"SonarPlugin":322112,"VoidList":755,"ACTEndcounter":46,"AutoTranslateXIV":1521,"CharSyncPlugin":32,"ChatTranslator":4562,"DomanMahjongStatus":149,"FantasyPlayer.Dalamud":4145,"HidePadlock":1177,"MPTimer":29,"MountCollectioner":500,"MouseTargetTooltip":677,"OhGeeCD":1263,"ResetAudio":2519,"SideHUDPlugin":855,"SizeMattersFishing":492,"SkillDisplay":1890,"SupineSnail.JobGaugeAdjustments":3653,"TabTab":38}