{"AccurateCountDown":{"count":12677},"AdventurerInNeed":{"count":5750},"AetherSense":{"count":3581},"BetterPartyFinder":{"count":1931},"BrowserHost.Plugin":{"count":5739},"BurntToast":{"count":415},"ChatCoordinates":{"count":5936},"ChatExtender":{"count":2633},"Dalamud.CharacterSync":{"count":9148},"Dalamud.DiscordBridge":{"count":5731},"Dalamud.LoadingImage":{"count":2878},"Dalamud.RichPresence":{"count":11858},"DalamudVox":{"count":24},"DamageInfoPlugin":{"count":17183},"ExpandedSearchInfo":{"count":1830},"FPSPlugin":{"count":14382},"FauxHollowsSolver":{"count":1268},"GatherBuddy":{"count":3317},"Globetrotter":{"count":19249},"GoodMemory":{"count":14194},"Housemate":{"count":2207},"HudSwap":{"count":2830},"ItemSearchPlugin":{"count":15958},"JobIcons":{"count":10915},"Kapture":{"count":2938},"MOAction":{"count":12844},"MacroRecursion":{"count":7764},"MapLinker":{"count":5566},"MarketBoardPlugin":{"count":20364},"MiniCactpotSolver":{"count":3025},"NeatNoter":{"count":5328},"NoSoliciting":{"count":19246},"OopsAllLalafells":{"count":7133},"PeepingTom":{"count":20320},"PennyPincher":{"count":13900},"PingPlugin":{"count":16566},"PixelPerfect":{"count":16693},"PlayerTrack":{"count":1619},"PrefPro":{"count":2900},"PriceCheck":{"count":17719},"QoLBar":{"count":8673},"RemindMe":{"count":10965},"RezPls":{"count":1219},"SimpleTweaksPlugin":{"count":13190},"SlideCast":{"count":19618},"SoundSetter":{"count":5433},"TeleporterPlugin":{"count":12382},"TextBoxStyler":{"count":435},"TextToTalk":{"count":1841},"TheGreatSeparator":{"count":1824},"TitleEdit":{"count":4814},"Tourist":{"count":2693},"VFXEditor":{"count":1237},"Visibility":{"count":6441},"VoidList":{"count":742},"WOLdo":{"count":1144},"WaymarkPresetPlugin":{"count":5789},"WondrousTailsSolver":{"count":2209},"XIVChat":{"count":2076},"XIVCombo":{"count":13718},"autoSweep":{"count":227},"orchestrion":{"count":9581},"owofy":{"count":23950}}